flake8_type_checking/__init__.py
flake8_type_checking/checker.py
flake8_type_checking/constants.py
flake8_type_checking/plugin.py
flake8_type_checking/py.typed
flake8_type_checking/types.py
flake8_type_checking/util.py
flake8_type_checking-3.1.1.dist-info/METADATA
flake8_type_checking-3.1.1.dist-info/WHEEL
flake8_type_checking-3.1.1.dist-info/entry_points.txt
flake8_type_checking-3.1.1.dist-info/licenses/LICENSE
flake8_type_checking-3.1.1.dist-info/RECORD
