Metadata-Version: 2.4
Name: flake8-type-checking
Version: 3.1.1
Summary: A flake8 plugin for managing type-checking imports & forward references
License: BSD-3-Clause
License-File: LICENSE
Keywords: flake8,plugin,linting,type hint,typing,imports
Author: Sondre Lillebø Gundersen
Author-email: sondrelg@live.no
Requires-Python: >=3.9
Classifier: Development Status :: 5 - Production/Stable
Classifier: Environment :: Console
Classifier: Intended Audience :: Developers
Classifier: License :: OSI Approved :: BSD License
Classifier: Operating System :: OS Independent
Classifier: Programming Language :: Python
Classifier: Programming Language :: Python :: 3
Classifier: Programming Language :: Python :: 3.9
Classifier: Programming Language :: Python :: 3.10
Classifier: Programming Language :: Python :: 3.11
Classifier: Programming Language :: Python :: 3.12
Classifier: Programming Language :: Python :: 3.13
Classifier: Programming Language :: Python :: 3.14
Classifier: Topic :: Software Development :: Quality Assurance
Classifier: Typing :: Typed
Requires-Dist: classify-imports
Requires-Dist: flake8
Project-URL: Homepage, https://github.com/snok
Project-URL: Repository, https://github.com/snok/flake8-type-checking
Project-URL: Releases, https://github.com/snok/flake8-type-checking/releases
